tech_discriptor/__init__.py
tech_discriptor/main.py
tech_discriptor/prompts.py
tech_discriptor-2025.12.21161904.dist-info/METADATA
tech_discriptor-2025.12.21161904.dist-info/WHEEL
tech_discriptor-2025.12.21161904.dist-info/top_level.txt
tech_discriptor-2025.12.21161904.dist-info/RECORD
