Metadata-Version: 2.4
Name: tech-discriptor
Version: 2025.12.21161904
Summary: A new package designed to transform technical descriptions of hardware or software solutions into structured summaries and feature lists. It takes detailed textual inputs about various systems like Ro
Author-email: tech-discriptor <hi@eugene.plus>
License: MIT
Project-URL: Homepage, https://github.com/chigwell/tech-discriptor
Requires-Python: >=3.9
Requires-Dist: langchain-llm7>=0.0.0
Requires-Dist: llmatch-messages>=0.0.0
Requires-Dist: langchain-core>=0.3.0
